langcompare/__init__.py
langcompare/main.py
langcompare/prompts.py
langcompare-2025.12.21132232.dist-info/METADATA
langcompare-2025.12.21132232.dist-info/WHEEL
langcompare-2025.12.21132232.dist-info/top_level.txt
langcompare-2025.12.21132232.dist-info/RECORD
