Metadata-Version: 2.4
Name: langcompare
Version: 2025.12.21132232
Summary: A new package that helps developers quickly compare programming languages (Java, JavaScript, Python, Go) for a given task or context. It takes a text input describing a development scenario or require
Author-email: langcompare <hi@eugene.plus>
License: MIT
Project-URL: Homepage, https://github.com/chigwell/langcompare
Requires-Python: >=3.9
Requires-Dist: langchain-llm7>=0.0.0
Requires-Dist: llmatch-messages>=0.0.0
Requires-Dist: langchain-core>=0.3.0
